sphinxcontrib/serializinghtml/__init__.py
sphinxcontrib/serializinghtml/jsonimpl.py
sphinxcontrib/serializinghtml/locales/sphinxcontrib.serializinghtml.pot
sphinxcontrib/serializinghtml/locales/.tx/config
sphinxcontrib/serializinghtml/locales/ar/LC_MESSAGES/sphinxcontrib.serializinghtml.mo
sphinxcontrib/serializinghtml/locales/ar/LC_MESSAGES/sphinxcontrib.serializinghtml.po
sphinxcontrib/serializinghtml/locales/bg/LC_MESSAGES/sphinxcontrib.serializinghtml.mo
sphinxcontrib/serializinghtml/locales/bg/LC_MESSAGES/sphinxcontrib.serializinghtml.po
sphinxcontrib/serializinghtml/locales/bn/LC_MESSAGES/sphinxcontrib.serializinghtml.mo
sphinxcontrib/serializinghtml/locales/bn/LC_MESSAGES/sphinxcontrib.serializinghtml.po
sphinxcontrib/serializinghtml/locales/ca/LC_MESSAGES/sphinxcontrib.serializinghtml.mo
sphinxcontrib/serializinghtml/locales/ca/LC_MESSAGES/sphinxcontrib.serializinghtml.po
sphinxcontrib/serializinghtml/locales/cak/LC_MESSAGES/sphinxcontrib.serializinghtml.mo
sphinxcontrib/serializinghtml/locales/cak/LC_MESSAGES/sphinxcontrib.serializinghtml.po
sphinxcontrib/serializinghtml/locales/cs/LC_MESSAGES/sphinxcontrib.serializinghtml.mo
sphinxcontrib/serializinghtml/locales/cs/LC_MESSAGES/sphinxcontrib.serializinghtml.po
sphinxcontrib/serializinghtml/locales/cy/LC_MESSAGES/sphinxcontrib.serializinghtml.mo
sphinxcontrib/serializinghtml/locales/cy/LC_MESSAGES/sphinxcontrib.serializinghtml.po
sphinxcontrib/serializinghtml/locales/da/LC_MESSAGES/sphinxcontrib.serializinghtml.mo
sphinxcontrib/serializinghtml/locales/da/LC_MESSAGES/sphinxcontrib.serializinghtml.po
sphinxcontrib/serializinghtml/locales/de/LC_MESSAGES/sphinxcontrib.serializinghtml.mo
sphinxcontrib/serializinghtml/locales/de/LC_MESSAGES/sphinxcontrib.serializinghtml.po
sphinxcontrib/serializinghtml/locales/el/LC_MESSAGES/sphinxcontrib.serializinghtml.mo
sphinxcontrib/serializinghtml/locales/el/LC_MESSAGES/sphinxcontrib.serializinghtml.po
sphinxcontrib_serializinghtml-1.1.6.dist-info/LICENSE
sphinxcontrib_serializinghtml-1.1.6.dist-info/WHEEL
sphinxcontrib_serializinghtml-1.1.6.dist-info/METADATA
sphinxcontrib_serializinghtml-1.1.6.dist-info/RECORD
